{"hourly": {"data": [{"precipProbability": 0, "apparentTemperature": 68.32, "time": 1495076400, "precipIntensity": 0, "ozone": 306.66, "windBearing": 230, "pressure": 1015.11, "icon": "clear-night", "humidity": 0.77, "visibility": 10, "summary": "Clear", "dewPoint": 60.7, "temperature": 68.32, "cloudCover": 0.15, "windSpeed": 7.53}, {"precipProbability": 0, "apparentTemperature": 67.04, "time": 1495080000, "precipIntensity": 0, "ozone": 306.42, "windBearing": 209, "pressure": 1015.09, "icon": "partly-cloudy-night", "humidity": 0.75, "visibility": 9.96, "summary": "Partly Cloudy", "dewPoint": 58.86, "temperature": 67.04, "cloudCover": 0.28, "windSpeed": 5.26}, {"precipProbability": 0, "apparentTemperature": 66.46, "time": 1495083600, "precipIntensity": 0, "ozone": 305.72, "windBearing": 195, "pressure": 1015.08, "icon": "partly-cloudy-night", "humidity": 0.74, "visibility": 9.68, "summary": "Partly Cloudy", "dewPoint": 58, "temperature": 66.46, "cloudCover": 0.36, "windSpeed": 4.95}, {"precipProbability": 0, "apparentTemperature": 66, "time": 1495087200, "precipIntensity": 0, "ozone": 305.3, "windBearing": 184, "pressure": 1015.09, "icon": "partly-cloudy-night", "humidity": 0.74, "visibility": 9.55, "summary": "Partly Cloudy", "dewPoint": 57.59, "temperature": 66, "cloudCover": 0.3, "windSpeed": 5.11}, {"precipProbability": 0, "apparentTemperature": 65.76, "time": 1495090800, "precipIntensity": 0, "ozone": 305.47, "windBearing": 181, "pressure": 1015.11, "icon": "partly-cloudy-night", "humidity": 0.73, "visibility": 9.49, "summary": "Mostly Cloudy", "dewPoint": 56.78, "temperature": 65.76, "cloudCover": 0.67, "windSpeed": 5.47}, {"precipProbability": 0, "apparentTemperature": 65.22, "time": 1495094400, "precipIntensity": 0, "ozone": 305.92, "windBearing": 183, "pressure": 1015.14, "icon": "partly-cloudy-night", "humidity": 0.71, "visibility": 9.54, "summary": "Mostly Cloudy", "dewPoint": 55.45, "temperature": 65.22, "cloudCover": 0.77, "windSpeed": 6.01}, {"precipProbability": 0, "apparentTemperature": 64.89, "time": 1495098000, "precipIntensity": 0, "ozone": 306.49, "windBearing": 186, "pressure": 1015.3, "icon": "partly-cloudy-night", "humidity": 0.69, "visibility": 9.68, "summary": "Mostly Cloudy", "dewPoint": 54.38, "temperature": 64.89, "cloudCover": 0.86, "windSpeed": 6.75}, {"precipProbability": 0, "apparentTemperature": 65.87, "time": 1495101600, "precipIntensity": 0, "ozone": 307.19, "windBearing": 188, "pressure": 1015.55, "icon": "partly-cloudy-night", "humidity": 0.68, "visibility": 9.69, "summary": "Mostly Cloudy", "dewPoint": 55.07, "temperature": 65.87, "cloudCover": 0.82, "windSpeed": 7.42}, {"precipProbability": 0, "apparentTemperature": 67.85, "time": 1495105200, "precipIntensity": 0, "ozone": 308.02, "windBearing": 190, "pressure": 1015.87, "icon": "partly-cloudy-day", "humidity": 0.68, "visibility": 9.72, "summary": "Mostly Cloudy", "dewPoint": 56.84, "temperature": 67.85, "cloudCover": 0.75, "windSpeed": 8.04}, {"precipProbability": 0, "apparentTemperature": 70.28, "time": 1495108800, "precipIntensity": 0, "ozone": 308.78, "windBearing": 195, "pressure": 1016.09, "icon": "partly-cloudy-day", "humidity": 0.66, "visibility": 9.99, "summary": "Mostly Cloudy", "dewPoint": 58.36, "temperature": 70.28, "cloudCover": 0.71, "windSpeed": 8.97}, {"precipProbability": 0, "apparentTemperature": 73.72, "time": 1495112400, "precipIntensity": 0, "ozone": 309.34, "windBearing": 204, "pressure": 1016.15, "icon": "partly-cloudy-day", "humidity": 0.62, "visibility": 10, "summary": "Mostly Cloudy", "dewPoint": 59.8, "temperature": 73.72, "cloudCover": 0.72, "windSpeed": 9.74}, {"precipProbability": 0, "apparentTemperature": 76.72, "time": 1495116000, "precipIntensity": 0, "ozone": 309.83, "windBearing": 212, "pressure": 1016.1, "icon": "partly-cloudy-day", "humidity": 0.6, "visibility": 10, "summary": "Mostly Cloudy", "dewPoint": 61.71, "temperature": 76.72, "cloudCover": 0.62, "windSpeed": 10.51}, {"precipProbability": 0, "apparentTemperature": 79.2, "time": 1495119600, "precipIntensity": 0, "ozone": 310.51, "windBearing": 215, "pressure": 1015.94, "icon": "partly-cloudy-day", "humidity": 0.58, "visibility": 10, "summary": "Mostly Cloudy", "dewPoint": 63.08, "temperature": 79.2, "cloudCover": 0.78, "windSpeed": 11.28}, {"precipProbability": 0, "apparentTemperature": 83.29, "time": 1495123200, "precipIntensity": 0, "ozone": 311.67, "windBearing": 213, "pressure": 1015.65, "icon": "partly-cloudy-day", "humidity": 0.57, "visibility": 9.52, "summary": "Mostly Cloudy", "dewPoint": 64.61, "temperature": 81.59, "cloudCover": 0.75, "windSpeed": 11.52}, {"precipProbability": 0, "apparentTemperature": 85.68, "time": 1495126800, "precipIntensity": 0, "ozone": 313.02, "windBearing": 212, "pressure": 1015.26, "icon": "partly-cloudy-day", "humidity": 0.56, "visibility": 8.88, "summary": "Mostly Cloudy", "dewPoint": 66.07, "temperature": 83.44, "cloudCover": 0.67, "windSpeed": 11.6}, {"precipProbability": 0, "apparentTemperature": 88.18, "time": 1495130400, "precipIntensity": 0, "ozone": 313.95, "windBearing": 210, "pressure": 1014.84, "icon": "partly-cloudy-day", "humidity": 0.55, "visibility": 8.56, "summary": "Mostly Cloudy", "dewPoint": 67.36, "temperature": 85.19, "cloudCover": 0.6, "windSpeed": 11.63}, {"precipProbability": 0, "apparentTemperature": 89.05, "time": 1495134000, "precipIntensity": 0, "ozone": 314.21, "windBearing": 209, "pressure": 1014.33, "icon": "partly-cloudy-day", "humidity": 0.54, "visibility": 8.88, "summary": "Partly Cloudy", "dewPoint": 67.51, "temperature": 85.91, "cloudCover": 0.55, "windSpeed": 12.01}, {"precipProbability": 0.01, "apparentTemperature": 88.58, "time": 1495137600, "precipIntensity": 0.001, "ozone": 314.06, "windBearing": 209, "pressure": 1013.79, "icon": "partly-cloudy-day", "humidity": 0.53, "precipType": "rain", "visibility": 9.53, "summary": "Partly Cloudy", "dewPoint": 66.87, "temperature": 85.81, "cloudCover": 0.51, "windSpeed": 12.06}, {"precipProbability": 0.01, "apparentTemperature": 88.34, "time": 1495141200, "precipIntensity": 0.0008, "ozone": 313.61, "windBearing": 210, "pressure": 1013.46, "icon": "partly-cloudy-day", "humidity": 0.54, "precipType": "rain", "visibility": 10, "summary": "Partly Cloudy", "dewPoint": 66.93, "temperature": 85.56, "cloudCover": 0.5, "windSpeed": 12}, {"precipProbability": 0, "apparentTemperature": 86.12, "time": 1495144800, "precipIntensity": 0, "ozone": 312.77, "windBearing": 212, "pressure": 1013.47, "icon": "partly-cloudy-day", "humidity": 0.56, "visibility": 10, "summary": "Partly Cloudy", "dewPoint": 66.38, "temperature": 83.74, "cloudCover": 0.52, "windSpeed": 10.72}, {"precipProbability": 0, "apparentTemperature": 83.62, "time": 1495148400, "precipIntensity": 0, "ozone": 311.63, "windBearing": 214, "pressure": 1013.72, "icon": "partly-cloudy-day", "humidity": 0.61, "visibility": 10, "summary": "Partly Cloudy", "dewPoint": 66.37, "temperature": 81.36, "cloudCover": 0.57, "windSpeed": 8.72}, {"precipProbability": 0, "apparentTemperature": 78.95, "time": 1495152000, "precipIntensity": 0, "ozone": 310.67, "windBearing": 217, "pressure": 1013.97, "icon": "partly-cloudy-day", "humidity": 0.64, "visibility": 9.82, "summary": "Mostly Cloudy", "dewPoint": 65.93, "temperature": 78.95, "cloudCover": 0.61, "windSpeed": 7.21}, {"precipProbability": 0.12, "apparentTemperature": 75.23, "time": 1495155600, "precipIntensity": 0.0034, "ozone": 310.12, "windBearing": 215, "pressure": 1014.37, "icon": "partly-cloudy-night", "humidity": 0.68, "precipType": "rain", "visibility": 8.02, "summary": "Mostly Cloudy", "dewPoint": 64.12, "temperature": 75.23, "cloudCover": 0.66, "windSpeed": 6.53}, {"precipProbability": 0.36, "apparentTemperature": 73.31, "time": 1495159200, "precipIntensity": 0.0073, "ozone": 309.74, "windBearing": 212, "pressure": 1014.89, "icon": "rain", "humidity": 0.71, "precipType": "rain", "visibility": 5.66, "summary": "Drizzle", "dewPoint": 63.3, "temperature": 73.31, "cloudCover": 0.73, "windSpeed": 6.54}, {"precipProbability": 0.5, "apparentTemperature": 71.77, "time": 1495162800, "precipIntensity": 0.0095, "ozone": 309.31, "windBearing": 209, "pressure": 1015.33, "icon": "rain", "humidity": 0.73, "precipType": "rain", "visibility": 4.5, "summary": "Light Rain", "dewPoint": 62.6, "temperature": 71.77, "cloudCover": 0.77, "windSpeed": 6.67}, {"precipProbability": 0.39, "apparentTemperature": 69.97, "time": 1495166400, "precipIntensity": 0.0077, "ozone": 308.56, "windBearing": 207, "pressure": 1015.52, "icon": "rain", "humidity": 0.77, "precipType": "rain", "visibility": 5.73, "summary": "Drizzle", "dewPoint": 62.36, "temperature": 69.97, "cloudCover": 0.74, "windSpeed": 6.73}, {"precipProbability": 0.16, "apparentTemperature": 68.36, "time": 1495170000, "precipIntensity": 0.0042, "ozone": 307.74, "windBearing": 204, "pressure": 1015.6, "icon": "partly-cloudy-night", "humidity": 0.81, "precipType": "rain", "visibility": 8.17, "summary": "Mostly Cloudy", "dewPoint": 62.28, "temperature": 68.36, "cloudCover": 0.64, "windSpeed": 6.83}, {"precipProbability": 0.09, "apparentTemperature": 67.08, "time": 1495173600, "precipIntensity": 0.0029, "ozone": 307.4, "windBearing": 202, "pressure": 1015.68, "icon": "partly-cloudy-night", "humidity": 0.85, "precipType": "rain", "visibility": 10, "summary": "Partly Cloudy", "dewPoint": 62.28, "temperature": 67.08, "cloudCover": 0.57, "windSpeed": 6.84}, {"precipProbability": 0.31, "apparentTemperature": 65.96, "time": 1495177200, "precipIntensity": 0.0066, "ozone": 307.79, "windBearing": 201, "pressure": 1015.76, "icon": "rain", "humidity": 0.88, "precipType": "rain", "visibility": 10, "summary": "Drizzle", "dewPoint": 62.19, "temperature": 65.96, "cloudCover": 0.46, "windSpeed": 6.67}, {"precipProbability": 0.54, "apparentTemperature": 63.88, "time": 1495180800, "precipIntensity": 0.0125, "ozone": 308.65, "windBearing": 202, "pressure": 1015.85, "icon": "rain", "humidity": 0.91, "precipType": "rain", "visibility": 10, "summary": "Light Rain", "dewPoint": 61.26, "temperature": 63.88, "cloudCover": 0.33, "windSpeed": 6.31}, {"precipProbability": 0.58, "apparentTemperature": 63.69, "time": 1495184400, "precipIntensity": 0.0163, "ozone": 309.69, "windBearing": 204, "pressure": 1016.05, "icon": "rain", "humidity": 0.93, "precipType": "rain", "visibility": 10, "summary": "Light Rain", "dewPoint": 61.61, "temperature": 63.69, "cloudCover": 0.3, "windSpeed": 5.91}, {"precipProbability": 0.57, "apparentTemperature": 64.86, "time": 1495188000, "precipIntensity": 0.016, "ozone": 311.04, "windBearing": 213, "pressure": 1016.49, "icon": "rain", "humidity": 0.94, "precipType": "rain", "visibility": 8.08, "summary": "Light Rain", "dewPoint": 63.12, "temperature": 64.86, "cloudCover": 0.41, "windSpeed": 5.72}, {"precipProbability": 0.55, "apparentTemperature": 67.11, "time": 1495191600, "precipIntensity": 0.0136, "ozone": 312.57, "windBearing": 225, "pressure": 1017.06, "icon": "rain", "humidity": 0.95, "precipType": "rain", "visibility": 5.52, "summary": "Light Rain", "dewPoint": 65.55, "temperature": 67.11, "cloudCover": 0.62, "windSpeed": 5.74}, {"precipProbability": 0.52, "apparentTemperature": 69.07, "time": 1495195200, "precipIntensity": 0.0109, "ozone": 313.57, "windBearing": 237, "pressure": 1017.52, "icon": "rain", "humidity": 0.94, "precipType": "rain", "visibility": 4.24, "summary": "Light Rain", "dewPoint": 67.41, "temperature": 69.07, "cloudCover": 0.78, "windSpeed": 5.72}, {"precipProbability": 0.41, "apparentTemperature": 71, "time": 1495198800, "precipIntensity": 0.0081, "ozone": 313.53, "windBearing": 247, "pressure": 1017.78, "icon": "rain", "humidity": 0.93, "precipType": "rain", "visibility": 5.52, "summary": "Drizzle", "dewPoint": 68.89, "temperature": 71, "cloudCover": 0.86, "windSpeed": 5.59}, {"precipProbability": 0.21, "apparentTemperature": 73.14, "time": 1495202400, "precipIntensity": 0.005, "ozone": 312.97, "windBearing": 256, "pressure": 1017.91, "icon": "rain", "humidity": 0.91, "precipType": "rain", "visibility": 8.08, "summary": "Drizzle", "dewPoint": 70.25, "temperature": 73.14, "cloudCover": 0.91, "windSpeed": 5.46}, {"precipProbability": 0.08, "apparentTemperature": 75.29, "time": 1495206000, "precipIntensity": 0.0027, "ozone": 312.69, "windBearing": 265, "pressure": 1017.98, "icon": "partly-cloudy-day", "humidity": 0.87, "precipType": "rain", "visibility": 10, "summary": "Mostly Cloudy", "dewPoint": 71.31, "temperature": 75.29, "cloudCover": 0.93, "windSpeed": 5.33}, {"precipProbability": 0.04, "apparentTemperature": 77.46, "time": 1495209600, "precipIntensity": 0.0018, "ozone": 313.16, "windBearing": 271, "pressure": 1017.98, "icon": "cloudy", "humidity": 0.83, "precipType": "rain", "visibility": 10, "summary": "Overcast", "dewPoint": 71.86, "temperature": 77.46, "cloudCover": 0.94, "windSpeed": 5.16}, {"precipProbability": 0.04, "apparentTemperature": 79.55, "time": 1495213200, "precipIntensity": 0.0017, "ozone": 313.92, "windBearing": 277, "pressure": 1017.9, "icon": "partly-cloudy-day", "humidity": 0.78, "precipType": "rain", "visibility": 10, "summary": "Mostly Cloudy", "dewPoint": 71.93, "temperature": 79.55, "cloudCover": 0.92, "windSpeed": 5.06}, {"precipProbability": 0.04, "apparentTemperature": 85.72, "time": 1495216800, "precipIntensity": 0.0017, "ozone": 314.45, "windBearing": 284, "pressure": 1017.77, "icon": "partly-cloudy-day", "humidity": 0.74, "precipType": "rain", "visibility": 10, "summary": "Mostly Cloudy", "dewPoint": 71.97, "temperature": 81.25, "cloudCover": 0.86, "windSpeed": 5.02}, {"precipProbability": 0.03, "apparentTemperature": 87.46, "time": 1495220400, "precipIntensity": 0.0015, "ozone": 314.55, "windBearing": 293, "pressure": 1017.5, "icon": "partly-cloudy-day", "humidity": 0.71, "precipType": "rain", "visibility": 10, "summary": "Mostly Cloudy", "dewPoint": 72.03, "temperature": 82.41, "cloudCover": 0.72, "windSpeed": 4.92}, {"precipProbability": 0.03, "apparentTemperature": 85.12, "time": 1495224000, "precipIntensity": 0.0014, "ozone": 314.42, "windBearing": 303, "pressure": 1017.19, "icon": "partly-cloudy-day", "humidity": 0.69, "precipType": "rain", "visibility": 10, "summary": "Partly Cloudy", "dewPoint": 70.33, "temperature": 81.35, "cloudCover": 0.53, "windSpeed": 4.83}, {"precipProbability": 0.05, "apparentTemperature": 78.62, "time": 1495227600, "precipIntensity": 0.002, "ozone": 314.06, "windBearing": 313, "pressure": 1017.11, "icon": "partly-cloudy-day", "humidity": 0.69, "precipType": "rain", "visibility": 10, "summary": "Partly Cloudy", "dewPoint": 67.73, "temperature": 78.62, "cloudCover": 0.38, "windSpeed": 4.7}, {"precipProbability": 0.16, "apparentTemperature": 75.22, "time": 1495231200, "precipIntensity": 0.0041, "ozone": 313.44, "windBearing": 324, "pressure": 1017.42, "icon": "partly-cloudy-day", "humidity": 0.72, "precipType": "rain", "visibility": 10, "summary": "Partly Cloudy", "dewPoint": 65.59, "temperature": 75.22, "cloudCover": 0.33, "windSpeed": 4.64}, {"precipProbability": 0.33, "apparentTemperature": 72.33, "time": 1495234800, "precipIntensity": 0.0068, "ozone": 312.6, "windBearing": 337, "pressure": 1018.05, "icon": "rain", "humidity": 0.77, "precipType": "rain", "visibility": 10, "summary": "Drizzle", "dewPoint": 64.58, "temperature": 72.33, "cloudCover": 0.33, "windSpeed": 4.89}, {"precipProbability": 0.42, "apparentTemperature": 69.96, "time": 1495238400, "precipIntensity": 0.0081, "ozone": 311.64, "windBearing": 349, "pressure": 1018.71, "icon": "rain", "humidity": 0.81, "precipType": "rain", "visibility": 10, "summary": "Drizzle", "dewPoint": 63.7, "temperature": 69.96, "cloudCover": 0.33, "windSpeed": 4.85}, {"precipProbability": 0.31, "apparentTemperature": 67.13, "time": 1495242000, "precipIntensity": 0.0065, "ozone": 310.5, "windBearing": 3, "pressure": 1019.42, "icon": "rain", "humidity": 0.83, "precipType": "rain", "visibility": 10, "summary": "Drizzle", "dewPoint": 61.73, "temperature": 67.13, "cloudCover": 0.33, "windSpeed": 4.66}, {"precipProbability": 0.12, "apparentTemperature": 63.68, "time": 1495245600, "precipIntensity": 0.0035, "ozone": 309.25, "windBearing": 17, "pressure": 1020.16, "icon": "partly-cloudy-night", "humidity": 0.84, "precipType": "rain", "visibility": 10, "summary": "Partly Cloudy", "dewPoint": 58.91, "temperature": 63.68, "cloudCover": 0.33, "windSpeed": 4.68}, {"precipProbability": 0.02, "apparentTemperature": 60.69, "time": 1495249200, "precipIntensity": 0.0012, "ozone": 308.12, "windBearing": 29, "pressure": 1020.67, "icon": "partly-cloudy-night", "humidity": 0.86, "precipType": "rain", "visibility": 10, "summary": "Partly Cloudy", "dewPoint": 56.43, "temperature": 60.69, "cloudCover": 0.35, "windSpeed": 4.86}], "summary": "Light rain tomorrow night.", "icon": "rain"}, "flags": {"lamp-stations": ["KCKB", "KMGW", "KW22"], "madis-stations": ["AR905", "AU535", "CRFW2", "D2853", "D3954", "D7807", "E4694", "E9539", "KCKB", "KGWW2", "KMGW", "LLPW2", "MORW2", "OAKM2", "WV014", "WV015"], "sources": ["lamp", "gfs", "cmc", "nam", "rap", "rtma", "sref", "fnmoc", "isd", "madis", "nearest-precip", "nwspa", "darksky"], "units": "us", "isd-stations": ["720328-63832", "724165-03725", "724165-99999", "724170-13729", "724175-03802", "724175-99999", "724176-13736", "724275-14894", "725117-04827", "725117-99999", "725205-14762", "999999-03729", "999999-03733", "999999-13729", "999999-13736", "999999-14762"]}, "longitude": -80.025285, "minutely": {"data": [{"precipProbability": 0, "time": 1495079100, "precipIntensity": 0}, {"precipProbability": 0, "time": 1495079160, "precipIntensity": 0}, {"precipProbability": 0, "time": 1495079220, "precipIntensity": 0}, {"precipProbability": 0, "time": 1495079280, "precipIntensity": 0}, {"precipProbability": 0, "time": 1495079340, "precipIntensity": 0}, {"precipProbability": 0, "time": 1495079400, "precipIntensity": 0}, {"precipProbability": 0, "time": 1495079460, "precipIntensity": 0}, {"precipProbability": 0, "time": 1495079520, "precipIntensity": 0}, {"precipProbability": 0, "time": 1495079580, "precipIntensity": 0}, {"precipProbability": 0, "time": 1495079640, "precipIntensity": 0}, {"precipProbability": 0, "time": 1495079700, "precipIntensity": 0}, {"precipProbability": 0, "time": 1495079760, "precipIntensity": 0}, {"precipProbability": 0, "time": 1495079820, "precipIntensity": 0}, {"precipProbability": 0, "time": 1495079880, "precipIntensity": 0}, {"precipProbability": 0, "time": 1495079940, "precipIntensity": 0}, {"precipProbability": 0, "time": 1495080000, "precipIntensity": 0}, {"precipProbability": 0, "time": 1495080060, "precipIntensity": 0}, {"precipProbability": 0, "time": 1495080120, "precipIntensity": 0}, {"precipProbability": 0, "time": 1495080180, "precipIntensity": 0}, {"precipProbability": 0, "time": 1495080240, "precipIntensity": 0}, {"precipProbability": 0, "time": 1495080300, "precipIntensity": 0}, {"precipProbability": 0, "time": 1495080360, "precipIntensity": 0}, {"precipProbability": 0, "time": 1495080420, "precipIntensity": 0}, {"precipProbability": 0, "time": 1495080480, "precipIntensity": 0}, {"precipProbability": 0, "time": 1495080540, "precipIntensity": 0}, {"precipProbability": 0, "time": 1495080600, "precipIntensity": 0}, {"precipProbability": 0, "time": 1495080660, "precipIntensity": 0}, {"precipProbability": 0, "time": 1495080720, "precipIntensity": 0}, {"precipProbability": 0, "time": 1495080780, "precipIntensity": 0}, {"precipProbability": 0, "time": 1495080840, "precipIntensity": 0}, {"precipProbability": 0, "time": 1495080900, "precipIntensity": 0}, {"precipProbability": 0, "time": 1495080960, "precipIntensity": 0}, {"precipProbability": 0, "time": 1495081020, "precipIntensity": 0}, {"precipProbability": 0, "time": 1495081080, "precipIntensity": 0}, {"precipProbability": 0, "time": 1495081140, "precipIntensity": 0}, {"precipProbability": 0, "time": 1495081200, "precipIntensity": 0}, {"precipProbability": 0, "time": 1495081260, "precipIntensity": 0}, {"precipProbability": 0, "time": 1495081320, "precipIntensity": 0}, {"precipProbability": 0, "time": 1495081380, "precipIntensity": 0}, {"precipProbability": 0, "time": 1495081440, "precipIntensity": 0}, {"precipProbability": 0, "time": 1495081500, "precipIntensity": 0}, {"precipProbability": 0, "time": 1495081560, "precipIntensity": 0}, {"precipProbability": 0, "time": 1495081620, "precipIntensity": 0}, {"precipProbability": 0, "time": 1495081680, "precipIntensity": 0}, {"precipProbability": 0, "time": 1495081740, "precipIntensity": 0}, {"precipProbability": 0, "time": 1495081800, "precipIntensity": 0}, {"precipProbability": 0, "time": 1495081860, "precipIntensity": 0}, {"precipProbability": 0, "time": 1495081920, "precipIntensity": 0}, {"precipProbability": 0, "time": 1495081980, "precipIntensity": 0}, {"precipProbability": 0, "time": 1495082040, "precipIntensity": 0}, {"precipProbability": 0, "time": 1495082100, "precipIntensity": 0}, {"precipProbability": 0, "time": 1495082160, "precipIntensity": 0}, {"precipProbability": 0, "time": 1495082220, "precipIntensity": 0}, {"precipProbability": 0, "time": 1495082280, "precipIntensity": 0}, {"precipProbability": 0, "time": 1495082340, "precipIntensity": 0}, {"precipProbability": 0, "time": 1495082400, "precipIntensity": 0}, {"precipProbability": 0, "time": 1495082460, "precipIntensity": 0}, {"precipProbability": 0, "time": 1495082520, "precipIntensity": 0}, {"precipProbability": 0, "time": 1495082580, "precipIntensity": 0}, {"precipProbability": 0, "time": 1495082640, "precipIntensity": 0}, {"precipProbability": 0, "time": 1495082700, "precipIntensity": 0}], "summary": "Partly cloudy for the hour.", "icon": "partly-cloudy-night"}, "currently": {"precipProbability": 0, "apparentTemperature": 67.04, "time": 1495079103, "precipIntensity": 0, "nearestStormDistance": 17, "pressure": 1015.1, "ozone": 306.48, "windBearing": 216, "visibility": 9.97, "icon": "partly-cloudy-night", "humidity": 0.75, "nearestStormBearing": 238, "summary": "Partly Cloudy", "dewPoint": 59.01, "temperature": 67.04, "cloudCover": 0.25, "windSpeed": 5.74}, "latitude": 39.522167, "offset": -4, "timezone": "America/New_York", "daily": {"data": [{"apparentTemperatureMin": 60.76, "temperatureMinTime": 1495011600, "temperatureMaxTime": 1495051200, "moonPhase": 0.71, "windBearing": 218, "icon": "partly-cloudy-night", "humidity": 0.64, "visibility": 9.31, "summary": "Partly cloudy overnight.", "dewPoint": 59.49, "cloudCover": 0.19, "sunriseTime": 1495015529, "precipProbability": 0, "temperatureMin": 60.76, "time": 1494993600, "apparentTemperatureMax": 87.59, "apparentTemperatureMinTime": 1495011600, "precipIntensity": 0, "ozone": 312.52, "pressure": 1015.49, "temperatureMax": 86.95, "sunsetTime": 1495067421, "apparentTemperatureMaxTime": 1495040400, "windSpeed": 6.33, "precipIntensityMax": 0}, {"apparentTemperatureMin": 64.89, "temperatureMinTime": 1495098000, "temperatureMaxTime": 1495134000, "moonPhase": 0.74, "windBearing": 205, "icon": "rain", "humidity": 0.64, "visibility": 9.22, "summary": "Light rain overnight.", "dewPoint": 61.83, "cloudCover": 0.63, "sunriseTime": 1495101879, "apparentTemperatureMinTime": 1495098000, "precipProbability": 0.5, "temperatureMin": 64.89, "time": 1495080000, "apparentTemperatureMax": 89.05, "precipIntensityMaxTime": 1495162800, "precipIntensity": 0.001, "ozone": 309.74, "precipType": "rain", "pressure": 1014.98, "temperatureMax": 85.91, "sunsetTime": 1495153876, "apparentTemperatureMaxTime": 1495134000, "windSpeed": 8.47, "precipIntensityMax": 0.0095}, {"apparentTemperatureMin": 60.69, "temperatureMinTime": 1495249200, "temperatureMaxTime": 1495220400, "moonPhase": 0.78, "windBearing": 257, "icon": "rain", "humidity": 0.83, "visibility": 9.05, "summary": "Light rain in the morning and evening.", "dewPoint": 65.64, "cloudCover": 0.58, "sunriseTime": 1495188232, "apparentTemperatureMinTime": 1495249200, "precipProbability": 0.58, "temperatureMin": 60.69, "time": 1495166400, "apparentTemperatureMax": 87.46, "precipIntensityMaxTime": 1495184400, "precipIntensity": 0.0061, "ozone": 311.51, "precipType": "rain", "pressure": 1017.46, "temperatureMax": 82.41, "sunsetTime": 1495240330, "apparentTemperatureMaxTime": 1495220400, "windSpeed": 3.07, "precipIntensityMax": 0.0163}, {"apparentTemperatureMin": 56.1, "temperatureMinTime": 1495267200, "temperatureMaxTime": 1495306800, "moonPhase": 0.81, "windBearing": 109, "icon": "rain", "humidity": 0.78, "visibility": 10, "summary": "Light rain until evening.", "dewPoint": 60.6, "cloudCover": 0.36, "sunriseTime": 1495274586, "apparentTemperatureMinTime": 1495267200, "precipProbability": 0.58, "temperatureMin": 56.1, "time": 1495252800, "apparentTemperatureMax": 90.12, "precipIntensityMaxTime": 1495281600, "precipIntensity": 0.0061, "ozone": 306.79, "precipType": "rain", "pressure": 1020.56, "temperatureMax": 84.23, "sunsetTime": 1495326784, "apparentTemperatureMaxTime": 1495306800, "windSpeed": 6.3, "precipIntensityMax": 0.017}, {"apparentTemperatureMin": 59.53, "temperatureMinTime": 1495357200, "temperatureMaxTime": 1495400400, "moonPhase": 0.85, "windBearing": 170, "icon": "rain", "humidity": 0.8, "visibility": 10, "summary": "Light rain throughout the day.", "dewPoint": 63.78, "cloudCover": 0.51, "sunriseTime": 1495360942, "apparentTemperatureMinTime": 1495357200, "precipProbability": 0.58, "temperatureMin": 59.53, "time": 1495339200, "apparentTemperatureMax": 87.98, "precipIntensityMaxTime": 1495386000, "precipIntensity": 0.007, "ozone": 306.58, "precipType": "rain", "pressure": 1017.84, "temperatureMax": 84.97, "sunsetTime": 1495413237, "apparentTemperatureMaxTime": 1495400400, "windSpeed": 6.02, "precipIntensityMax": 0.0163}, {"apparentTemperatureMin": 56.56, "temperatureMinTime": 1495508400, "temperatureMaxTime": 1495425600, "moonPhase": 0.88, "windBearing": 247, "icon": "rain", "humidity": 0.88, "summary": "Light rain in the morning and afternoon.", "dewPoint": 58.25, "cloudCover": 0.92, "sunriseTime": 1495447299, "apparentTemperatureMinTime": 1495508400, "precipProbability": 0.67, "temperatureMin": 56.56, "time": 1495425600, "apparentTemperatureMax": 70.52, "precipIntensityMaxTime": 1495454400, "precipIntensity": 0.0109, "ozone": 317.33, "precipType": "rain", "pressure": 1012.05, "temperatureMax": 70.52, "sunsetTime": 1495499689, "apparentTemperatureMaxTime": 1495425600, "windSpeed": 5.97, "precipIntensityMax": 0.0326}, {"apparentTemperatureMin": 50.83, "temperatureMinTime": 1495530000, "temperatureMaxTime": 1495569600, "moonPhase": 0.92, "windBearing": 236, "icon": "partly-cloudy-day", "humidity": 0.7, "summary": "Partly cloudy throughout the day.", "dewPoint": 51.08, "cloudCover": 0.42, "sunriseTime": 1495533658, "apparentTemperatureMinTime": 1495530000, "precipProbability": 0.11, "temperatureMin": 50.83, "time": 1495512000, "apparentTemperatureMax": 73.99, "precipIntensityMaxTime": 1495594800, "precipIntensity": 0.0018, "ozone": 352.35, "precipType": "rain", "pressure": 1010.96, "temperatureMax": 73.99, "sunsetTime": 1495586141, "apparentTemperatureMaxTime": 1495569600, "windSpeed": 4.94, "precipIntensityMax": 0.0033}, {"apparentTemperatureMin": 50.78, "temperatureMinTime": 1495609200, "temperatureMaxTime": 1495641600, "moonPhase": 0.95, "windBearing": 221, "icon": "rain", "humidity": 0.8, "summary": "Light rain starting in the afternoon.", "dewPoint": 53.28, "cloudCover": 0.65, "sunriseTime": 1495620019, "apparentTemperatureMinTime": 1495609200, "precipProbability": 0.7, "temperatureMin": 50.78, "time": 1495598400, "apparentTemperatureMax": 69.19, "precipIntensityMaxTime": 1495663200, "precipIntensity": 0.0114, "ozone": 362.58, "precipType": "rain", "pressure": 1006.61, "temperatureMax": 69.19, "sunsetTime": 1495672591, "apparentTemperatureMaxTime": 1495641600, "windSpeed": 4.9, "precipIntensityMax": 0.0419}], "summary": "Light rain tomorrow through Wednesday, with temperatures falling to 69\u00b0F on Wednesday.", "icon": "rain"}}